mcp_server_restart/__init__.py
mcp_server_restart/server.py
mcp_server_restart-0.1.2.dist-info/METADATA
mcp_server_restart-0.1.2.dist-info/WHEEL
mcp_server_restart-0.1.2.dist-info/entry_points.txt
mcp_server_restart-0.1.2.dist-info/licenses/LICENSE
mcp_server_restart-0.1.2.dist-info/RECORD
