Metadata-Version: 2.3
Name: mcp-server-restart
Version: 0.1.2
Summary: MCP server for restarting Claude Desktop
Project-URL: Homepage, https://github.com/non-dirty/mcp-server-restart
Project-URL: Repository, https://github.com/non-dirty/mcp-server-restart.git
Project-URL: Issues, https://github.com/non-dirty/mcp-server-restart/issues
Author-email: Matthew Smith <non_dirty@me.com>
License: MIT
Keywords: claude,desktop,mcp,restart
Classifier: Development Status :: 4 - Beta
Classifier: Environment :: Console
Classifier: Intended Audience :: Developers
Classifier: License :: OSI Approved :: MIT License
Classifier: Operating System :: MacOS
Classifier: Programming Language :: Python :: 3
Classifier: Programming Language :: Python :: 3.13
Classifier: Topic :: Software Development :: Libraries :: Python Modules
Requires-Python: >=3.13
Requires-Dist: mcp>=1.0.0
Requires-Dist: psutil>=6.1.0
Requires-Dist: pydantic>=2.10.2
Provides-Extra: dev
Requires-Dist: pytest; extra == 'dev'
Requires-Dist: pytest-asyncio; extra == 'dev'
